[
	{
		"__TYPE__": "SharedSliceContent",
		"variation": "default",
		"primary": {
			"heading": {
				"__TYPE__": "FieldContent",
				"value": "scared",
				"type": "Text"
			},
			"item": {
				"__TYPE__": "GroupContentType",
				"value": [
					{
						"__TYPE__": "GroupItemContent",
						"value": [
							[
								"tech_name",
								{
									"__TYPE__": "FieldContent",
									"value": "street",
									"type": "Text"
								}
							],
							[
								"tech_color",
								{
									"__TYPE__": "FieldContent",
									"value": "#fb2abc",
									"type": "Color"
								}
							]
						]
					}
				]
			}
		},
		"items": []
	}
]